odoo10_addon_mail_optional_follower_notification-10.0.1.0.2-py3.8-nspkg.pth
odoo/addons/mail_optional_follower_notification/README.rst
odoo/addons/mail_optional_follower_notification/__init__.py
odoo/addons/mail_optional_follower_notification/__manifest__.py
odoo/addons/mail_optional_follower_notification/i18n/am.po
odoo/addons/mail_optional_follower_notification/i18n/ar.po
odoo/addons/mail_optional_follower_notification/i18n/bg.po
odoo/addons/mail_optional_follower_notification/i18n/bs.po
odoo/addons/mail_optional_follower_notification/i18n/ca.po
odoo/addons/mail_optional_follower_notification/i18n/cs.po
odoo/addons/mail_optional_follower_notification/i18n/da.po
odoo/addons/mail_optional_follower_notification/i18n/de.po
odoo/addons/mail_optional_follower_notification/i18n/el_GR.po
odoo/addons/mail_optional_follower_notification/i18n/en.po
odoo/addons/mail_optional_follower_notification/i18n/en_GB.po
odoo/addons/mail_optional_follower_notification/i18n/es.po
odoo/addons/mail_optional_follower_notification/i18n/es_CO.po
odoo/addons/mail_optional_follower_notification/i18n/es_CR.po
odoo/addons/mail_optional_follower_notification/i18n/es_EC.po
odoo/addons/mail_optional_follower_notification/i18n/es_MX.po
odoo/addons/mail_optional_follower_notification/i18n/es_VE.po
odoo/addons/mail_optional_follower_notification/i18n/et.po
odoo/addons/mail_optional_follower_notification/i18n/eu.po
odoo/addons/mail_optional_follower_notification/i18n/fi.po
odoo/addons/mail_optional_follower_notification/i18n/fr.po
odoo/addons/mail_optional_follower_notification/i18n/fr_CA.po
odoo/addons/mail_optional_follower_notification/i18n/fr_CH.po
odoo/addons/mail_optional_follower_notification/i18n/gl.po
odoo/addons/mail_optional_follower_notification/i18n/hr.po
odoo/addons/mail_optional_follower_notification/i18n/hr_HR.po
odoo/addons/mail_optional_follower_notification/i18n/hu.po
odoo/addons/mail_optional_follower_notification/i18n/it.po
odoo/addons/mail_optional_follower_notification/i18n/ja.po
odoo10_addon_mail_optional_follower_notification-10.0.1.0.2.dist-info/METADATA
odoo10_addon_mail_optional_follower_notification-10.0.1.0.2.dist-info/WHEEL
odoo10_addon_mail_optional_follower_notification-10.0.1.0.2.dist-info/namespace_packages.txt
odoo10_addon_mail_optional_follower_notification-10.0.1.0.2.dist-info/top_level.txt
odoo10_addon_mail_optional_follower_notification-10.0.1.0.2.dist-info/RECORD
